{
    "id": 1,
    "name": "Jesus",
    "lastName": "DeLaFerrere",
    "dni": "1234567",
    "cuil": "1234566",
    "email": "jesus@cielo.com",
    "tel": 1234567,
    "cel": 1234567,
    "reputation": 10.0,
    "type": "affiliate",
    "img": null,
    "audit": {
        "createDate": "2013-10-10",
        "editDate": null,
        "deleteDate": null,
        "createUser": "GuzmanClaudia",
        "editUser": null,
        "deleteUser": null
    },
    "address": {
        "street": "Avenida Del Juego de la Oca",
        "number": 123,
        "department": null,
        "floor": null,
        "city": "Campana",
        "cp": "1234",
        "prov": "Buenos Aires",
        "country": "Argentina"
    },
    "lends": [{
        "id": 2,
        "type": "foreign",
        "lendingDate": 1385694000000,
        "expectedReturnDate": 1388372400000,
        "comments": "Salio nuevo",
        "copy": {
            "id": 2,
            "title": "Harry Potter y La Piedra Filosofal"
        }
    }],
    "isSuspended": true
}